moolb/__init__.py
moolb/moolb.py
moolb-0.1.0.dist-info/METADATA
moolb-0.1.0.dist-info/WHEEL
moolb-0.1.0.dist-info/top_level.txt
moolb-0.1.0.dist-info/RECORD
